chronotco/__init__.py
chronotco/chronotco.py
chronotco-0.0.1.dist-info/LICENSE
chronotco-0.0.1.dist-info/METADATA
chronotco-0.0.1.dist-info/WHEEL
chronotco-0.0.1.dist-info/top_level.txt
chronotco-0.0.1.dist-info/RECORD
