Metadata-Version: 2.1
Name: chronotco
Version: 0.0.1
Summary: Python3 decorator for tail call optimization via bytecode injection.
Home-page: https://github.com/the-chronomancer/chronotco
Author: Jacob Coleman
Author-email: chronomancy.io@gmail.com
License: Copyleft
Platform: UNKNOWN
Classifier: Development Status :: 3 - Alpha
Classifier: Intended Audience :: Science/Research
Classifier: Programming Language :: Python :: 3 :: Only
Classifier: License :: OSI Approved :: GNU General Public License v3 or later (GPLv3+)
Classifier: Natural Language :: English
Requires-Dist: dis
